<?xml version="1.0" encoding="UTF-8"?>
<LanguageData>
  
  <!-- EN: army cap -->
  <DMS_Apparel_ArmyCap.label>army cap</DMS_Apparel_ArmyCap.label>
  <!-- EN: a soft cap for service man when combat helmet is not required. -->
  <DMS_Apparel_ArmyCap.description>a soft cap for service man when combat helmet is not required.</DMS_Apparel_ArmyCap.description>
  
  <!-- EN: operator helmet -->
  <DMS_Apparel_ArrayHelmet.label>operator helmet</DMS_Apparel_ArrayHelmet.label>
  <!-- EN: A full-covered helmet designed for field drone operators, Features built-in head-mounted display and neural-connected operating system. can not only increase the control bandwidth but also give full protection. -->
  <DMS_Apparel_ArrayHelmet.description>A full-covered helmet designed for field drone operators, Features built-in head-mounted display and neural-connected operating system. can not only increase the control bandwidth but also give full protection.</DMS_Apparel_ArrayHelmet.description>
  
  <!-- EN: beret -->
  <DMS_Apparel_Beret.label>beret</DMS_Apparel_Beret.label>
  <!-- EN: a soft cap for military man when combat helmet is not required. -->
  <DMS_Apparel_Beret.description>a soft cap for military man when combat helmet is not required.</DMS_Apparel_Beret.description>
  
  <!-- EN: bionic suit -->
  <DMS_Apparel_BionicSuit.label>bionic suit</DMS_Apparel_BionicSuit.label>
  <!-- EN: Physical enhancement equipment sewn from artificial muscle fibers. Can effectively increase the wearer's muscle strength and mobility. -->
  <DMS_Apparel_BionicSuit.description>Physical enhancement equipment sewn from artificial muscle fibers. Can effectively increase the wearer's muscle strength and mobility.</DMS_Apparel_BionicSuit.description>
  
  <!-- EN: soft kepi -->
  <DMS_Apparel_SoftKepi.label>soft kepi</DMS_Apparel_SoftKepi.label>
  <!-- EN: a soft cap for military man when combat helmet is not required. -->
  <DMS_Apparel_SoftKepi.description>a soft cap for military man when combat helmet is not required.</DMS_Apparel_SoftKepi.description>
  
  <!-- EN: tactical helmet -->
  <DMS_Apparel_TacticalHelmet.label>tactical helmet</DMS_Apparel_TacticalHelmet.label>
  <!-- EN: A lightweight combat helmet with a complex design, reinforced with plasteel. Not effective against blunt weapons. -->
  <DMS_Apparel_TacticalHelmet.description>A lightweight combat helmet with a complex design, reinforced with plasteel. Not effective against blunt weapons.</DMS_Apparel_TacticalHelmet.description>
  
  <!-- EN: tactical vest -->
  <DMS_Apparel_TacticalVest.label>tactical vest</DMS_Apparel_TacticalVest.label>
  <!-- EN: A vest with armor plates inserted on the chest and back. While quite effective at deflecting gunshots and stabbing attacks against the chest, it does nothing to protect the limbs. -->
  <DMS_Apparel_TacticalVest.description>A vest with armor plates inserted on the chest and back. While quite effective at deflecting gunshots and stabbing attacks against the chest, it does nothing to protect the limbs.</DMS_Apparel_TacticalVest.description>
  
</LanguageData>